ls_imports.py
ls_imports-0.1.2.dist-info/LICENSE.txt
ls_imports-0.1.2.dist-info/METADATA
ls_imports-0.1.2.dist-info/WHEEL
ls_imports-0.1.2.dist-info/entry_points.txt
ls_imports-0.1.2.dist-info/top_level.txt
ls_imports-0.1.2.dist-info/RECORD
