Metadata-Version: 2.1
Name: ls-imports
Version: 0.1.2
Summary: Search Python source file(s) for imported modules.
Author-email: Peter Talley <peterctalley@gmail.com>
License: MIT
Project-URL: Homepage, https://github.com/otaithleigh/ls-imports
Classifier: Environment :: Console
Classifier: License :: OSI Approved :: MIT License
Classifier: Operating System :: OS Independent
Classifier: Programming Language :: Python :: 3
Classifier: Topic :: Utilities
Requires-Python: >=3.10
License-File: LICENSE.txt
Requires-Dist: click
